gilman_fasta_edit/__init__.py
gilman_fasta_edit/main.py
gilman_fasta_edit-0.1.dist-info/METADATA
gilman_fasta_edit-0.1.dist-info/WHEEL
gilman_fasta_edit-0.1.dist-info/entry_points.txt
gilman_fasta_edit-0.1.dist-info/top_level.txt
gilman_fasta_edit-0.1.dist-info/RECORD
