Metadata-Version: 2.1
Name: gilman_fasta_edit
Version: 0.1
Summary: A tool to rename contigs in a FASTA file.
Requires-Dist: biopython
